yta_constants/__init__.py
yta_constants/audio.py
yta_constants/color.py
yta_constants/enum.py
yta_constants/ffmpeg.py
yta_constants/file.py
yta_constants/google_drive.py
yta_constants/image.py
yta_constants/lang.py
yta_constants/manim.py
yta_constants/masking.py
yta_constants/moviepy.py
yta_constants/multimedia.py
yta_constants/project.py
yta_constants/regex.py
yta_constants/text.py
yta_constants/video.py
yta_constants-0.0.57.dist-info/licenses/LICENSE
yta_constants-0.0.57.dist-info/METADATA
yta_constants-0.0.57.dist-info/WHEEL
yta_constants-0.0.57.dist-info/RECORD
