Metadata-Version: 2.4
Name: yta-constants
Version: 0.0.57
Summary: Youtube Autonomous Constants Module
License-File: LICENSE
Author: danialcala94
Author-email: danielalcalavalera@gmail.com
Requires-Python: ==3.9
Classifier: Programming Language :: Python :: 3
Classifier: Programming Language :: Python :: 3.9
Requires-Dist: exrex (>=0.12.0,<1.0.0)
Requires-Dist: yta_validation (>=0.0.1,<1.0.0)
